optima_0_1/__init__.py
optima_0_1/cli.py
optima_0_1/config.py
optima_0_1/constants.py
optima_0_1/commands/__init__.py
optima_0_1/commands/op_create.py
optima_0_1/commands/op_download.py
optima_0_1/commands/op_upload.py
optima_0_1/commands/op_utils.py
optima_0_1/commands/op_view.py
optima_0_1/services/__init__.py
optima_0_1/services/api_client.py
optima_0_1/services/cli_handler.py
optima_0_1/services/cli_messages.py
optima_0_1/services/cli_prompts.py
optima_0_1/services/cli_validation.py
optima_0_1/services/db_services.py
optima_0_1/services/mf_upload.py
optima_0_1/services/mf_utils.py
optima_0_1/unimelb-mf-clients-0.7.8/bin/unix/aterm
optima_0_1/unimelb-mf-clients-0.7.8/bin/unix/aterm-download
optima_0_1/unimelb-mf-clients-0.7.8/bin/unix/aterm-gui
optima_0_1/unimelb-mf-clients-0.7.8/bin/unix/aterm-import
optima_0_1/unimelb-mf-clients-0.7.8/bin/unix/download-id-shell-script-url-create
optima_0_1/unimelb-mf-clients-0.7.8/bin/unix/download-namespace-shell-script-url-create
optima_0_1/unimelb-mf-clients-0.7.8/bin/unix/file-list
optima_0_1/unimelb-mf-clients-0.7.8/bin/unix/instrument-upload-list
optima_0_1/unimelb-mf-clients-0.7.8/bin/unix/instrument-upload-missing-find
optima_0_1/unimelb-mf-clients-0.7.8/bin/unix/scp-get
optima_0_1/unimelb-mf-clients-0.7.8/bin/unix/scp-put
optima_0_1/unimelb-mf-clients-0.7.8/bin/unix/sftp-get
optima_0_1/unimelb-mf-clients-0.7.8/bin/unix/sftp-put
optima_0_1/unimelb-mf-clients-0.7.8/bin/unix/unimelb-mf-archive
optima_0_1/unimelb-mf-clients-0.7.8/bin/unix/unimelb-mf-check
optima_0_1/unimelb-mf-clients-0.7.8/bin/unix/unimelb-mf-download
optima_0_1/unimelb-mf-clients-0.7.8/bin/unix/unimelb-mf-import-archive
optima_0_1/unimelb-mf-clients-0.7.8/bin/unix/unimelb-mf-instrument-upload
optima_0_1/unimelb-mf-clients-0.7.8/bin/unix/unimelb-mf-perf
optima_0_1/unimelb-mf-clients-0.7.8/bin/unix/unimelb-mf-upload
optima_0_1/unimelb-mf-clients-0.7.8/bin/unix/facility/facility-download-aterm-script-url-create
optima_0.1-0.1.7.dist-info/METADATA
optima_0.1-0.1.7.dist-info/WHEEL
optima_0.1-0.1.7.dist-info/entry_points.txt
optima_0.1-0.1.7.dist-info/top_level.txt
optima_0.1-0.1.7.dist-info/RECORD
