Metadata-Version: 2.1
Name: optima-0.1
Version: 0.1.7
Summary: OPTIMA CLI
Author: Ashley Wang
Author-email: xiaohuyaw@gmail.com
Classifier: Programming Language :: Python :: 3
Classifier: License :: OSI Approved :: MIT License
Classifier: Operating System :: OS Independent
Requires-Python: >=3.11
Requires-Dist: click >=8.1.0
Requires-Dist: python-dotenv >=0.19.0
Requires-Dist: requests >=2.32.0
Requires-Dist: setuptools >=74.1.0
